py12flogging/__init__.py
py12flogging/log_formatter.py
py12flogging/pprint.py
py12flogging-0.8.0.dist-info/licenses/LICENSE.txt
py12flogging-0.8.0.dist-info/METADATA
py12flogging-0.8.0.dist-info/WHEEL
py12flogging-0.8.0.dist-info/top_level.txt
py12flogging-0.8.0.dist-info/RECORD
