Metadata-Version: 2.4
Name: py12flogging
Version: 0.8.0
Summary: Python logging module for developing microservices conforming to 12 Factor App methodology.
Home-page: https://gitlab.tuni.fi/fsd/py12flogging
Author: Toni Sissala
Author-email: support.fsd+py12flogging@tuni.fi
License: EUPL v1.2
Classifier: Development Status :: 5 - Production/Stable
Classifier: Environment :: Console
Classifier: Intended Audience :: Developers
Classifier: License :: OSI Approved :: European Union Public Licence 1.2 (EUPL 1.2)
Classifier: Programming Language :: Python
Classifier: Topic :: Software Development :: Libraries :: Python Modules
License-File: LICENSE.txt
Dynamic: author
Dynamic: author-email
Dynamic: classifier
Dynamic: description
Dynamic: description-content-type
Dynamic: home-page
Dynamic: license
Dynamic: license-file
Dynamic: summary
